{
  "tags": {
    "example": "```tsx\n<ComboBox.Trigger>\n  <ComboBox.TagGroup />\n  <ComboBox.Input />\n</ComboBox.Trigger>\n```",
    "supportsStyleProps": ""
  },
  "filePath": "/Users/byronwall/workspaces/ct/nimbus/packages/nimbus/src/index.ts",
  "description": "# ComboBox.TagGroup\n\nDisplays selected items as tags in multi-select mode.\nUses Nimbus TagGroup component which reads from TagGroupContext.\n\nTagGroupContext (provided by custom context provider) includes:\n- items: selected items array from collection\n- onRemove: handler to remove tags\n- size: tag size variant\n- aria-label: accessible label\n- selectionMode: \"none\" for tags\n- disabledKeys: disabled tag keys\n\nOnly renders content in multi-select mode.",
  "displayName": "ComboBoxTagGroup",
  "methods": [],
  "props": {},
  "supportsStyleProps": true
}